LICENSE
README.md
setup.py
PySideX/__init__.py
PySideX.egg-info/PKG-INFO
PySideX.egg-info/SOURCES.txt
PySideX.egg-info/dependency_links.txt
PySideX.egg-info/requires.txt
PySideX.egg-info/top_level.txt
PySideX/Assets/__init__.py
PySideX/Components/__init__.py
PySideX/Components/box.py
PySideX/Widgets/__init__.py
PySideX/Widgets/button.py
PySideX/Widgets/dropdawn.py
PySideX/Widgets/frame.py
PySideX/Widgets/horizontalBoxLayout.py
PySideX/Widgets/image.py
PySideX/Widgets/input.py
PySideX/Widgets/label.py
PySideX/Widgets/messagebox.py
PySideX/Widgets/spacerItem.py
PySideX/Widgets/textArea.py
PySideX/Widgets/verticalBoxLayout.py
PySideX/Widgets/window.py