Metadata-Version: 2.1
Name: PySideX
Version: 0.0.9
Summary: Unofficial PySide6 library, produced with the aim of facilitating the construction of more elegant and improved interfaces using PySide6 technology
Author: Ryan Souza Anselmo
Author-email: ryansouza.cwb@email.com
License: MIT License
Keywords: pysidex
License-File: LICENSE
